[
    {
        "url": "http://www.jwz.org/blog/feed/",
        "title": "jwz"
    },
    {
        "url": "http://ludopoitou.wordpress.com/feed/",
        "title": "Ludo's Sketches"
    },
    {
        "url": "http://marginnotes2.wordpress.com/feed/",
        "title": "Margin Notes 2.0"
    },
    {
        "url": "https://www.tbray.org/ongoing/ongoing.atom",
        "title": "ongoing by Tim Bray"
    },
    {
        "url": "http://www.schneier.com/blog/atom.xml",
        "title": "Schneier on Security"
    }
]